stash_basic/__init__.py
stash_basic/accounts_handler.py
stash_basic/initializer.py
stash_basic/main.py
stash_basic/transactions_handler.py
stash_basic/utils.py
stash_basic-1.0.0.dist-info/entry_points.txt
stash_basic-1.0.0.dist-info/licenses/LICENSE
stash_basic-1.0.0.dist-info/WHEEL
stash_basic-1.0.0.dist-info/METADATA
stash_basic-1.0.0.dist-info/RECORD
