Metadata-Version: 2.4
Name: stash-basic
Version: 1.0.0
Summary: The CLI tool for recording all your money related transactions!
Keywords: cli,personal finance,budget,transactions,money
Author-email: Sumeet Hande <hande.sumeet38@gmail.com>
Requires-Python: >=3.10
Classifier: Programming Language :: Python :: 3
Classifier: License :: OSI Approved :: MIT License
Classifier: Operating System :: OS Independent
Classifier: Environment :: Console
Classifier: Intended Audience :: End Users/Desktop
Classifier: Topic :: Office/Business :: Financial
License-File: LICENSE
Requires-Dist: click>=8.1
Requires-Dist: tabulate>=0.8.0
